Metadata-Version: 2.1
Name: mrwn-distributions
Version: 0.1
Summary: Gaussian and Binomial distributions
Author: Marwan Musa
Author-email: marwanlmusa@gmail.com
